{"type":"FeatureCollection","features":[{"type": "Feature", "id": "hXVo-8nNQvzK2Wks_kRle3YS40I=", "properties": {"ref": "{D91CCC6D-87D6-487F-B7E4-C2ED59C8373F}", "@spider": "alnatura_de", "addr:street": "Bismarckstr. 27-29", "addr:city": "K\u00f6ln", "addr:postcode": "50672", "addr:country": "Deutschland", "name": "Alnatura Super Natur Markt", "opening_hours": "Mo-Sa 08:00-20:00"}, "geometry": {"type": "Point", "coordinates": [6.935816, 50.941469]}}]}